server.py
mseep_storyblok_mcp_server-1.0.3.dist-info/licenses/LICENSE
mseep_storyblok_mcp_server-1.0.3.dist-info/METADATA
mseep_storyblok_mcp_server-1.0.3.dist-info/WHEEL
mseep_storyblok_mcp_server-1.0.3.dist-info/entry_points.txt
mseep_storyblok_mcp_server-1.0.3.dist-info/top_level.txt
mseep_storyblok_mcp_server-1.0.3.dist-info/RECORD
