Metadata-Version: 2.4
Name: mseep-storyblok-mcp-server
Version: 1.0.3
Summary: MCP server for storyblok
Author-email: mseep <support@skydeck.ai>
Requires-Python: >=3.10
License-File: LICENSE
Requires-Dist: httpx>=0.28.1
Requires-Dist: mcp[cli]>=1.9.4
Requires-Dist: python-dotenv>=1.1.0
Requires-Dist: requests>=2.32.4
Dynamic: license-file
